ecpy/__init__.py
ecpy/borromean.py
ecpy/curve_defs.py
ecpy/curves.py
ecpy/ecdsa.py
ecpy/ecrand.py
ecpy/ecschnorr.py
ecpy/eddsa.py
ecpy/formatters.py
ecpy/keys.py
ECPy-1.2.4.dist-info/LICENSE
ECPy-1.2.4.dist-info/METADATA
ECPy-1.2.4.dist-info/WHEEL
ECPy-1.2.4.dist-info/top_level.txt
ECPy-1.2.4.dist-info/RECORD
