Metadata-Version: 2.1
Name: ECPy
Version: 1.2.4
Summary: Pure Pyhton Elliptic Curve Library
Home-page: https://github.com/cslashm/ECPy
Author: Cedric Mesnil
Author-email: cslashm@gmail.com
License: Apache License - Version 2.0
Keywords: ecdsa eddsa ed25519 ed448 schnorr ecschnorr elliptic curve
Platform: UNKNOWN
Classifier: Programming Language :: Python :: 2.7
Classifier: Programming Language :: Python :: 3
Classifier: Development Status :: 4 - Beta
Classifier: License :: OSI Approved :: Apache Software License
Classifier: Topic :: Security :: Cryptography
Provides: ecpy
